encapsulation/__init__.py
encapsulation/adaptors.py
encapsulation/base.py
encapsulation/extensions.py
encapsulation-0.2.2.dist-info/LICENSE.txt
encapsulation-0.2.2.dist-info/METADATA
encapsulation-0.2.2.dist-info/WHEEL
encapsulation-0.2.2.dist-info/top_level.txt
encapsulation-0.2.2.dist-info/RECORD
