Metadata-Version: 2.1
Name: encapsulation
Version: 0.2.2
Summary: Encapsulation and decorators made easy.
Home-page: https://github.com/JungeWerther/From
Author: Seb Wiechers
Author-email: 
Classifier: Programming Language :: Python :: 3
Classifier: License :: OSI Approved :: MIT License
Classifier: Operating System :: OS Independent
Requires-Python: >=3.6
License-File: LICENSE.txt
